brave_deepseek_book_search/__init__.py
brave_deepseek_book_search/cli.py
brave_deepseek_book_search/models.py
brave_deepseek_book_search/search.py
brave_deepseek_book_search-1.0.0.dist-info/METADATA
brave_deepseek_book_search-1.0.0.dist-info/WHEEL
brave_deepseek_book_search-1.0.0.dist-info/entry_points.txt
brave_deepseek_book_search-1.0.0.dist-info/licenses/LICENSE
brave_deepseek_book_search-1.0.0.dist-info/RECORD
