Metadata-Version: 2.4
Name: brave-deepseek-book-search
Version: 1.0.0
Summary: Intelligent book search using Brave Search API + DeepSeek LLM
Project-URL: Homepage, https://github.com/example/brave-deepseek-book-search
Project-URL: Documentation, https://github.com/example/brave-deepseek-book-search#readme
Project-URL: Repository, https://github.com/example/brave-deepseek-book-search.git
Project-URL: Issues, https://github.com/example/brave-deepseek-book-search/issues
Author-email: Brave-DeepSeek Team <team@example.com>
License: MIT License
License-File: LICENSE
Classifier: Development Status :: 4 - Beta
Classifier: Intended Audience :: Developers
Classifier: License :: OSI Approved :: MIT License
Classifier: Programming Language :: Python :: 3
Classifier: Programming Language :: Python :: 3.8
Classifier: Programming Language :: Python :: 3.9
Classifier: Programming Language :: Python :: 3.10
Classifier: Programming Language :: Python :: 3.11
Classifier: Topic :: Internet :: WWW/HTTP :: Indexing/Search
Classifier: Topic :: Software Development :: Libraries :: Python Modules
Requires-Python: >=3.8
Requires-Dist: pydantic>=1.8.0
Requires-Dist: requests>=2.25.0
Provides-Extra: dev
Requires-Dist: black>=21.0.0; extra == 'dev'
Requires-Dist: flake8>=3.8.0; extra == 'dev'
Requires-Dist: mypy>=0.800; extra == 'dev'
Requires-Dist: pytest>=6.0.0; extra == 'dev'
